axis_order_cache/__init__.py
axis_order_cache/apps.py
axis_order_cache/exceptions.py
axis_order_cache/models.py
axis_order_cache/registry.py
axis_order_cache/settings.py
axis_order_cache/utils.py
django_axis_order-0.1.1.dist-info/LICENSE
django_axis_order-0.1.1.dist-info/METADATA
django_axis_order-0.1.1.dist-info/WHEEL
django_axis_order-0.1.1.dist-info/top_level.txt
django_axis_order-0.1.1.dist-info/RECORD
