Metadata-Version: 2.1
Name: django-axis-order
Version: 0.1.1
Summary: Small django app to cache reference systems from the epsg registry and provide the correct axis order.
Home-page: https://github.com/mrmap-community/django-axis-order
Author: mrmap-commuity
Author-email: jonas.kiefer@live.com
License: MIT
Platform: UNKNOWN
Classifier: Development Status :: 5 - Production/Stable
Classifier: Intended Audience :: Developers
Classifier: Natural Language :: English
Classifier: Programming Language :: Python :: 3.8
Classifier: Programming Language :: Python :: 3.9
Classifier: Programming Language :: Python :: 3.10
Classifier: Programming Language :: Python :: 3.11
Classifier: Topic :: Internet :: WWW/HTTP
Classifier: Environment :: Web Environment
Classifier: Framework :: Django
Classifier: Topic :: Software Development :: Libraries
Classifier: License :: OSI Approved :: MIT License
Classifier: Operating System :: OS Independent
Requires-Python: >=3.8
License-File: LICENSE
Requires-Dist: django (>=3.2)
Requires-Dist: requests (>=2.23.0)
